beespammer/__init__.py
beespammer/__main__.py
beespammer/spammer.py
beespammer-4.0.0.dist-info/entry_points.txt
beespammer-4.0.0.dist-info/LICENSE
beespammer-4.0.0.dist-info/WHEEL
beespammer-4.0.0.dist-info/METADATA
beespammer-4.0.0.dist-info/RECORD
