Metadata-Version: 2.1
Name: beespammer
Version: 4.0.0
Summary: Spam Text
Author: Eliaz Bobadilla
Author-email: eliaz.bobadilladev@gmail.com
Requires-Python: >=3.7,<4.0
Classifier: Programming Language :: Python :: 3
Classifier: Programming Language :: Python :: 3.7
Classifier: Programming Language :: Python :: 3.8
Classifier: Programming Language :: Python :: 3.9
Requires-Dist: PyAutoGUI (>=0.9.53,<0.10.0)
